nutstore_cli/__init__.py
nutstore_cli/cli.py
nutstore_cli/command_help.py
nutstore_cli/completer.py
nutstore_cli/config.py
nutstore_cli/context.py
nutstore_cli/execution.py
nutstore_cli/client/__init__.py
nutstore_cli/client/base.py
nutstore_cli/client/client.py
nutstore_cli/client/exceptions.py
nutstore_cli/client/path_helper.py
nutstore_cli/client/utils.py
nutstore_cli/utils/__init__.py
nutstore_cli/utils/codecs.py
nutstore_cli/utils/functional.py
nutstore_cli/utils/output.py
nutstore_cli-0.4.3.dist-info/DESCRIPTION.rst
nutstore_cli-0.4.3.dist-info/METADATA
nutstore_cli-0.4.3.dist-info/RECORD
nutstore_cli-0.4.3.dist-info/WHEEL
nutstore_cli-0.4.3.dist-info/entry_points.txt
nutstore_cli-0.4.3.dist-info/metadata.json
nutstore_cli-0.4.3.dist-info/pbr.json
nutstore_cli-0.4.3.dist-info/top_level.txt
