Metadata-Version: 2.0
Name: nutstore-cli
Version: 0.4.3
Summary: A command-line interface for NutStore based on WebDAV.
Home-page: https://github.com/Kxrr/nutstore-cli
Author: Kxrr
Author-email: hi@kxrr.us
License: MIT
Keywords: nutstore
Requires-Dist: easywebdav (==1.2.0)
Requires-Dist: six (==1.10.0)
Requires-Dist: parsimonious (==0.7.0)
Requires-Dist: python-dateutil (==2.6.0)
Requires-Dist: click (==6.7)
Requires-Dist: prompt-toolkit (==1.0.9)
Requires-Dist: tabulate (==0.7.7)
